curie/__init__.py
curie/__main__.py
curie/connect.py
curie/dag.py
curie/document.py
curie/modes.py
curie/static/XXX.zip
curie/static/__init__.py
curie/static/jinja/__init__.py
curie/static/jinja/docs-settings.yaml.j2
curie/static/jinja/pipeline.md.j2
curie/static/jinja/project.md.j2
curie/utils/__init__.py
curie/utils/awsboto.py
curie/utils/docs.py
curie/utils/jinja.py
curie/utils/paths.py
curieDEPR/__init__.py
curieDEPR/__main__.py
curieDEPR/inca.py
curieDEPR/lab.py
curieDEPR/mk.py
curieDEPR/sources.py
curieDEPR/defaults/__init__.py
curieDEPR/defaults/jinja/__init__.py
curieDEPR/utils/__init__.py
curieDEPR/utils/secrets.py
pycurie-0.1.16.dist-info/METADATA
pycurie-0.1.16.dist-info/WHEEL
pycurie-0.1.16.dist-info/entry_points.txt
pycurie-0.1.16.dist-info/top_level.txt
pycurie-0.1.16.dist-info/RECORD
