Metadata-Version: 2.1
Name: pycurie
Version: 0.1.16
Home-page: https://github.com/EricDiGi/CurieKetl
Author: Eric DiGioacchino
Keywords: etl,data,data engineering,data science,mlops,devops
Classifier: Development Status :: 1 - Planning
Classifier: Intended Audience :: Developers
Classifier: Programming Language :: Python :: 3
Requires-Dist: PyYAML
Requires-Dist: Jinja2
Requires-Dist: boto3
Requires-Dist: python-dotenv
Requires-Dist: pandas
Requires-Dist: IPython
Requires-Dist: sqlparse
